YouTubeMusicAPI.py
YouTubeMusicAPI-2.9.1.dist-info/LICENSE
YouTubeMusicAPI-2.9.1.dist-info/METADATA
YouTubeMusicAPI-2.9.1.dist-info/WHEEL
YouTubeMusicAPI-2.9.1.dist-info/top_level.txt
YouTubeMusicAPI-2.9.1.dist-info/RECORD
