Metadata-Version: 2.1
Name: YouTubeMusicAPI
Version: 2.9.1
Summary: An unofficial search API for YouTube Music.
Home-page: https://github.com/cj-praveen/YouTube-Music-API/
Keywords: youtube music api,YouTubeMusicAPI,python youtube music api,youtube music api python
Requires-Python: >=3.9
License-File: LICENSE
Requires-Dist: httpx
